pygroupcache/__init__.py
pygroupcache/groupcache.py
pygroupcache/test_groupcache.py
pygroupcache/libs/groupcache.h
pygroupcache/libs/groupcache.so
pygroupcache/libs/groupcache_41bb18b.h
pygroupcache/libs/groupcache_41bb18b.so
pygroupcache-1.0.1.dist-info/LICENSE
pygroupcache-1.0.1.dist-info/METADATA
pygroupcache-1.0.1.dist-info/WHEEL
pygroupcache-1.0.1.dist-info/top_level.txt
pygroupcache-1.0.1.dist-info/RECORD
